odoo/addons/hr_employee_medical_examination/README.rst
odoo/addons/hr_employee_medical_examination/__init__.py
odoo/addons/hr_employee_medical_examination/__manifest__.py
odoo/addons/hr_employee_medical_examination/i18n/de.po
odoo/addons/hr_employee_medical_examination/i18n/es.po
odoo/addons/hr_employee_medical_examination/i18n/fr.po
odoo/addons/hr_employee_medical_examination/i18n/hr.po
odoo/addons/hr_employee_medical_examination/i18n/hr_employee_medical_examination.pot
odoo/addons/hr_employee_medical_examination/i18n/it.po
odoo/addons/hr_employee_medical_examination/models/__init__.py
odoo/addons/hr_employee_medical_examination/models/hr_employee.py
odoo/addons/hr_employee_medical_examination/models/hr_employee_medical_examination.py
odoo/addons/hr_employee_medical_examination/readme/CONTRIBUTORS.md
odoo/addons/hr_employee_medical_examination/readme/DESCRIPTION.md
odoo/addons/hr_employee_medical_examination/readme/USAGE.md
odoo/addons/hr_employee_medical_examination/security/hr_employee_medical_examination_security.xml
odoo/addons/hr_employee_medical_examination/security/ir.model.access.csv
odoo/addons/hr_employee_medical_examination/static/description/icon.png
odoo/addons/hr_employee_medical_examination/static/description/index.html
odoo/addons/hr_employee_medical_examination/tests/__init__.py
odoo/addons/hr_employee_medical_examination/tests/test_hr_employee_medical_examination.py
odoo/addons/hr_employee_medical_examination/views/hr_employee_medical_examination_views.xml
odoo/addons/hr_employee_medical_examination/views/hr_employee_views.xml
odoo/addons/hr_employee_medical_examination/wizards/__init__.py
odoo/addons/hr_employee_medical_examination/wizards/wizard_generate_medical_examination.py
odoo/addons/hr_employee_medical_examination/wizards/wizard_generate_medical_examination.xml
odoo_addon_hr_employee_medical_examination-18.0.1.1.0.3.dist-info/METADATA
odoo_addon_hr_employee_medical_examination-18.0.1.1.0.3.dist-info/WHEEL
odoo_addon_hr_employee_medical_examination-18.0.1.1.0.3.dist-info/top_level.txt
odoo_addon_hr_employee_medical_examination-18.0.1.1.0.3.dist-info/RECORD
