Metadata-Version: 2.1
Name: odoo-addon-hr_employee_medical_examination
Version: 18.0.1.1.0.3
Requires-Python: >=3.10
Requires-Dist: odoo==18.0.*
Summary: Adds information about employee's medical examinations
Home-page: https://github.com/OCA/hr
License: AGPL-3
Author: Creu Blanca, Odoo Community Association (OCA)
Author-email: support@odoo-community.org
Classifier: Programming Language :: Python
Classifier: Framework :: Odoo
Classifier: Framework :: Odoo :: 18.0
Classifier: License :: OSI Approved :: GNU Affero General Public License v3
